rpicontrols/__init__.py
rpicontrols/controller.py
rpicontrols/gpio_driver.py
rpicontrols/py.typed
rpicontrols/rpi_gpio_driver.py
rpi_controls-1.0.3.dist-info/LICENSE
rpi_controls-1.0.3.dist-info/WHEEL
rpi_controls-1.0.3.dist-info/METADATA
rpi_controls-1.0.3.dist-info/RECORD
