Metadata-Version: 2.1
Name: rpi-controls
Version: 1.0.3
Summary: Library that eases interacting with physical buttons through the Raspberry Pi GPIO
Home-page: https://github.com/2franix/rpi-controls
License: GPL-3.0-or-later
Author: Cyrille Defranoux
Maintainer: Cyrille Defranoux
Maintainer-email: cyrille.github@defx.fr
Requires-Python: >=3.7,<4.0
Classifier: Development Status :: 5 - Production/Stable
Classifier: License :: OSI Approved :: GNU General Public License v3 or later (GPLv3+)
Classifier: Operating System :: OS Independent
Classifier: Programming Language :: Python :: 3
Classifier: Programming Language :: Python :: 3.10
Classifier: Programming Language :: Python :: 3.11
Classifier: Programming Language :: Python :: 3.7
Classifier: Programming Language :: Python :: 3.8
Classifier: Programming Language :: Python :: 3.9
Classifier: Topic :: Software Development :: Libraries :: Python Modules
Requires-Dist: RPi.GPIO (>=0.7.1,<0.8.0)
Requires-Dist: importlib-metadata (>=4.11.3,<5.0.0)
Project-URL: Bug Tracker, https://github.com/2franix/rpi-controls/issues
Project-URL: Documentation, https://rpi-controls.readthedocs.io/en/latest/
Project-URL: Repository, https://github.com/2franix/rpi-controls
